translateturbo/__init__.py
translateturbo/main.py
translateturbo-0.0.1.dist-info/METADATA
translateturbo-0.0.1.dist-info/WHEEL
translateturbo-0.0.1.dist-info/top_level.txt
translateturbo-0.0.1.dist-info/RECORD
